raztodo/__init__.py
raztodo/__main__.py
raztodo/application/__init__.py
raztodo/application/use_case_factory.py
raztodo/application/use_cases/__init__.py
raztodo/application/use_cases/clear_tasks.py
raztodo/application/use_cases/create_task.py
raztodo/application/use_cases/delete_task.py
raztodo/application/use_cases/export_task.py
raztodo/application/use_cases/import_task.py
raztodo/application/use_cases/list_tasks.py
raztodo/application/use_cases/mark_task_done.py
raztodo/application/use_cases/migrate_tasks.py
raztodo/application/use_cases/search_tasks.py
raztodo/application/use_cases/update_task.py
raztodo/domain/__init__.py
raztodo/domain/exceptions.py
raztodo/domain/task_entity.py
raztodo/domain/task_repository.py
raztodo/infrastructure/__init__.py
raztodo/infrastructure/container.py
raztodo/infrastructure/logger.py
raztodo/infrastructure/settings.py
raztodo/infrastructure/sqlite/__init__.py
raztodo/infrastructure/sqlite/connection.py
raztodo/infrastructure/sqlite/migrations.py
raztodo/infrastructure/sqlite/task_dao.py
raztodo/infrastructure/sqlite/task_mapper.py
raztodo/infrastructure/sqlite/task_repository.py
raztodo/infrastructure/sqlite/task_schema.py
raztodo/presentation/__init__.py
raztodo/presentation/cli/__init__.py
raztodo/presentation/cli/entrypoint.py
raztodo/presentation/cli/formatters.py
raztodo/presentation/cli/helpers.py
raztodo/presentation/cli/parser.py
raztodo/presentation/cli/router.py
raztodo/presentation/cli/commands/__init__.py
raztodo/presentation/cli/commands/clear_tasks_cmd.py
raztodo/presentation/cli/commands/create_task_cmd.py
raztodo/presentation/cli/commands/delete_task_cmd.py
raztodo/presentation/cli/commands/export_task_cmd.py
raztodo/presentation/cli/commands/import_task_cmd.py
raztodo/presentation/cli/commands/list_tasks_cmd.py
raztodo/presentation/cli/commands/mark_task_done_cmd.py
raztodo/presentation/cli/commands/migrate_tasks_cmd.py
raztodo/presentation/cli/commands/search_tasks_cmd.py
raztodo-0.2.1.dist-info/METADATA
raztodo-0.2.1.dist-info/WHEEL
raztodo-0.2.1.dist-info/entry_points.txt
raztodo-0.2.1.dist-info/licenses/LICENSE
raztodo-0.2.1.dist-info/RECORD
