Metadata-Version: 2.4
Name: raztodo
Version: 0.2.1
Summary: A fast, zero-dependency command-line todo/task manager using SQLite.
Project-URL: Homepage, https://github.com/razbuild/raztodo
Project-URL: Repository, https://github.com/razbuild/raztodo
Project-URL: issues, https://github.com/razbuild/raztodo/issues
Author-email: Raz <real.raz.dev@gmail.com>
License-Expression: MIT
License-File: LICENSE
Keywords: cli,command-line,python,task,todo
Classifier: Development Status :: 5 - Production/Stable
Classifier: Environment :: Console
Classifier: Intended Audience :: End Users/Desktop
Classifier: Operating System :: OS Independent
Classifier: Programming Language :: Python :: 3.13
Classifier: Programming Language :: Python :: 3.14
Classifier: Topic :: Utilities
Requires-Python: >=3.13
Requires-Dist: raztint
Provides-Extra: coverage
Requires-Dist: coverage; extra == 'coverage'
Provides-Extra: dev
Requires-Dist: black; extra == 'dev'
Requires-Dist: coverage; extra == 'dev'
Requires-Dist: mypy; extra == 'dev'
Requires-Dist: pytest; extra == 'dev'
Requires-Dist: ruff; extra == 'dev'
Provides-Extra: formatter
Requires-Dist: black; extra == 'formatter'
Provides-Extra: lint
Requires-Dist: ruff; extra == 'lint'
Provides-Extra: test
Requires-Dist: pytest; extra == 'test'
Provides-Extra: typecheck
Requires-Dist: mypy; extra == 'typecheck'
